ecs/__init__.py
ecs/entity.py
ecs/essentials.py
ecs/metasystem.py
ecs/system.py
ecs_girvel-3.0.1.dist-info/METADATA
ecs_girvel-3.0.1.dist-info/WHEEL
ecs_girvel-3.0.1.dist-info/top_level.txt
ecs_girvel-3.0.1.dist-info/RECORD
