Metadata-Version: 2.1
Name: ecs-girvel
Version: 3.0.1
Summary: Annotation-based asynchronous ECS library
Home-page: https://github.com/girvel/ecs
Author: Nikita Girvel Dobrynin
Author-email: widauka@ya.ru
Classifier: Programming Language :: Python :: 3
Classifier: License :: OSI Approved :: MIT License
Classifier: Operating System :: OS Independent
Requires-Python: >=3.7
